neocore_sdk/__init__.py
neocore_sdk/canonicalization.py
neocore_sdk/client.py
neocore_sdk/crypto.py
neocore_sdk/exceptions.py
neocore_sdk/key_loader.py
neocore_sdk/cli/__init__.py
neocore_sdk/cli/keygen.py
neocore_sdk/cli/verify_key.py
neocore_sdk-1.0.0.dist-info/licenses/LICENSE
neocore_sdk-1.0.0.dist-info/METADATA
neocore_sdk-1.0.0.dist-info/WHEEL
neocore_sdk-1.0.0.dist-info/entry_points.txt
neocore_sdk-1.0.0.dist-info/top_level.txt
neocore_sdk-1.0.0.dist-info/RECORD
