Metadata-Version: 2.4
Name: neocore-sdk
Version: 1.0.0
Summary: Official Python client SDK for NeoCore API authentication using Ed25519 signatures
Author-email: NeoSapien <support@neosapien.xyz>
License: Apache License 2.0
Project-URL: Homepage, https://neosapien.xyz
Project-URL: Documentation, https://docs.neosapien.xyz
Project-URL: Repository, https://github.com/NeoSapien-xyz/neocore-sdk
Project-URL: Issues, https://github.com/NeoSapien-xyz/neocore-sdk/issues
Keywords: neocore,security,ed25519,authentication,api,sdk,cryptography
Classifier: Development Status :: 5 - Production/Stable
Classifier: Intended Audience :: Developers
Classifier: License :: OSI Approved :: Apache Software License
Classifier: Programming Language :: Python :: 3
Classifier: Programming Language :: Python :: 3.9
Classifier: Programming Language :: Python :: 3.10
Classifier: Programming Language :: Python :: 3.11
Classifier: Programming Language :: Python :: 3.12
Classifier: Topic :: Security :: Cryptography
Classifier: Topic :: Software Development :: Libraries :: Python Modules
Requires-Python: >=3.9
License-File: LICENSE
Requires-Dist: cryptography>=41.0.0
Requires-Dist: requests>=2.31.0
Provides-Extra: dev
Requires-Dist: pytest>=7.4.0; extra == "dev"
Requires-Dist: pytest-cov>=4.1.0; extra == "dev"
Requires-Dist: black>=23.7.0; extra == "dev"
Requires-Dist: ruff>=0.0.285; extra == "dev"
Requires-Dist: mypy>=1.5.0; extra == "dev"
Requires-Dist: types-requests>=2.31.0; extra == "dev"
Requires-Dist: build>=0.10.0; extra == "dev"
Dynamic: license-file
